LICENSE
README.md
setup.py
SonaDB.egg-info/PKG-INFO
SonaDB.egg-info/SOURCES.txt
SonaDB.egg-info/dependency_links.txt
SonaDB.egg-info/top_level.txt
sonadb/__init__.py
sonadb/database.py