Metadata-Version: 2.1
Name: SonaDB
Version: 2.2.2
Summary: Key-Value database library, small and easy to use.
Home-page: https://github.com/ZSendokame/SonaDB
Author: ZSendokame
License: MIT license
Platform: UNKNOWN
License-File: LICENSE
